README.md
setup.cfg
setup.py
intouch_client.egg-info/PKG-INFO
intouch_client.egg-info/SOURCES.txt
intouch_client.egg-info/dependency_links.txt
intouch_client.egg-info/top_level.txt
intouchclient/__init__.py