Metadata-Version: 2.1
Name: intouch-client
Version: 0.2.4.post0
Summary: A aiohttp-based client for Intergas Intouch Lan2RF systems
Home-page: https://github.com/zxdavb/intouch-client
Author: David Bonnes
Author-email: zxdavb@gmail.com
License: UNKNOWN
Download-URL: https://github.com/zxdavb/intouch-client/archive/VERSION.tar.gz
Keywords: intergas,intouch,lan2rf
Platform: UNKNOWN
Classifier: Programming Language :: Python :: 3
Classifier: License :: OSI Approved :: MIT License
Classifier: Operating System :: OS Independent
Classifier: Development Status :: 7 - Inactive
